pyOASIS/DTEC_CALC.py
pyOASIS/RNX_CLEAN.py
pyOASIS/RNX_LEVELLING.py
pyOASIS/RNX_SCREENING.py
pyOASIS/ROTI_CALC.py
pyOASIS/SIDX_CALC.py
pyOASIS/SP3_INTERPOLATE.py
pyOASIS/__init__.py
pyOASIS/glonass_channels.dat
pyOASIS/gnss_freqs.py
pyOASIS/levelling_settings.py
pyOASIS/linear_combinations.py
pyOASIS/screening_settings.py
pyOASIS/settings.py
pyOASIS-1.0.3.dist-info/LICENSE
pyOASIS-1.0.3.dist-info/METADATA
pyOASIS-1.0.3.dist-info/WHEEL
pyOASIS-1.0.3.dist-info/top_level.txt
pyOASIS-1.0.3.dist-info/RECORD
