Metadata-Version: 2.1
Name: pyOASIS
Version: 1.0.3
Summary: Open-Access System for Ionospheric Studies (OASIS)
Home-page: https://github.com/giorgiopicanco/OASIS
Author: Giorgio Picanço
Author-email: giorgiopicanco@gmail.com
Classifier: Development Status :: 5 - Production/Stable
Classifier: Programming Language :: Python :: 3
Classifier: License :: OSI Approved :: MIT License
Classifier: Operating System :: OS Independent
Classifier: Intended Audience :: Science/Research
Classifier: Topic :: Scientific/Engineering :: Atmospheric Science
Requires-Python: >=3.8
License-File: LICENSE
Requires-Dist: astropy
Requires-Dist: georinex
Requires-Dist: matplotlib
Requires-Dist: numpy
Requires-Dist: pandas
Requires-Dist: pyproj
Requires-Dist: scipy
